pve_utils/commands/__init__.py
pve_utils/commands/create_lxc.py
pve_utils/commands/shell_lxc.py
pve_utils/commands/transport_lxc.py
pve_utils/config.py
pve_utils/resources/__init__.py
pve_utils/resources/proxmox_container.py
pve_utils/resources/proxmox_node.py
pve_utils/utils/__init__.py
pve_utils/utils/decorators.py
pve_utils/utils/pprint.py
pve_utils/utils/ssh.py
pve_utils-1.3.0.dist-info/LICENSE.md
pve_utils-1.3.0.dist-info/METADATA
pve_utils-1.3.0.dist-info/WHEEL
pve_utils-1.3.0.dist-info/entry_points.txt
pve_utils-1.3.0.dist-info/RECORD
